advio/__init__.py
advio/cli.py
advio/config.py
advio/tg.py
advio/utils.py
advio/version.py
advio-0.1.1.dist-info/licenses/LICENSE
advio-0.1.1.dist-info/METADATA
advio-0.1.1.dist-info/WHEEL
advio-0.1.1.dist-info/entry_points.txt
advio-0.1.1.dist-info/top_level.txt
advio-0.1.1.dist-info/RECORD
