Metadata-Version: 2.4
Name: advio
Version: 0.1.1
Summary: Smart tool for sending automated
Author-email: Abbas Bachari <abbas-bachari@hotmail.com>
License-Expression: MIT
Project-URL: Homepage, https://github.com/abbas-bachari/advio
Project-URL: Documentation, https://github.com/abbas-bachari/advio#readme
Project-URL: Source, https://github.com/abbas-bachari/advio
Keywords: advertising,automation,marketing,bot,telegram
Classifier: Intended Audience :: Developers
Classifier: Programming Language :: Python :: 3.10
Classifier: Programming Language :: Python :: 3.11
Classifier: Programming Language :: Python :: 3.12
Classifier: Operating System :: OS Independent
Requires-Python: >=3.10
License-File: LICENSE
Requires-Dist: teloxi>=1.0.1
Requires-Dist: dbflux>=1.0.2
Requires-Dist: loguru>=0.7.3
Requires-Dist: colored>=2.3.0
Dynamic: license-file
